pyDEA/__init__.py
pyDEA/logging_config.ini
pyDEA/main.py
pyDEA/main_gui.py
pyDEA/pyDEAlogo.gif
pyDEA/pyDEAlogo.ico
pyDEA/core/__init__.py
pyDEA/core/data_processing/__init__.py
pyDEA/core/data_processing/input_data.py
pyDEA/core/data_processing/parameters.py
pyDEA/core/data_processing/read_data_from_xls.py
pyDEA/core/data_processing/save_data_to_file.py
pyDEA/core/data_processing/solution.py
pyDEA/core/data_processing/solution_text_writer.py
pyDEA/core/data_processing/targets_and_slacks.py
pyDEA/core/data_processing/write_data_to_xls.py
pyDEA/core/data_processing/xlsx_workbook.py
pyDEA/core/gui_modules/__init__.py
pyDEA/core/gui_modules/categories_checkbox_gui.py
pyDEA/core/gui_modules/custom_canvas_gui.py
pyDEA/core/gui_modules/data_frame_gui.py
pyDEA/core/gui_modules/data_tab_frame_gui.py
pyDEA/core/gui_modules/load_xls_gui.py
pyDEA/core/gui_modules/navigation_frame_gui.py
pyDEA/core/gui_modules/options_frame_gui.py
pyDEA/core/gui_modules/params_frame_gui.py
pyDEA/core/gui_modules/scrollable_frame_gui.py
pyDEA/core/gui_modules/solution_frame_gui.py
pyDEA/core/gui_modules/solution_tab_frame_gui.py
pyDEA/core/gui_modules/table_gui.py
pyDEA/core/gui_modules/table_modifier_gui.py
pyDEA/core/gui_modules/text_for_weights_gui.py
pyDEA/core/gui_modules/text_frame_gui.py
pyDEA/core/gui_modules/weight_frame_gui.py
pyDEA/core/models/__init__.py
pyDEA/core/models/bound_generators.py
pyDEA/core/models/categorical_dmus.py
pyDEA/core/models/envelopment_model.py
pyDEA/core/models/envelopment_model_base.py
pyDEA/core/models/envelopment_model_decorators.py
pyDEA/core/models/input_output_model_bases.py
pyDEA/core/models/maximize_slacks.py
pyDEA/core/models/model_base.py
pyDEA/core/models/model_progress_bar_decorator.py
pyDEA/core/models/multiplier_model.py
pyDEA/core/models/multiplier_model_base.py
pyDEA/core/models/multiplier_model_decorators.py
pyDEA/core/models/peel_the_onion.py
pyDEA/core/models/super_efficiency_model.py
pyDEA-1.6.dist-info/DESCRIPTION.rst
pyDEA-1.6.dist-info/METADATA
pyDEA-1.6.dist-info/RECORD
pyDEA-1.6.dist-info/WHEEL
pyDEA-1.6.dist-info/entry_points.txt
pyDEA-1.6.dist-info/metadata.json
pyDEA-1.6.dist-info/top_level.txt
