Metadata-Version: 2.0
Name: pyDEA
Version: 1.6
Summary: Package for conducting data envelopment analysis
Home-page: https://github.com/araith/pyDEA
Author: Andrea Raith, Olga Perederieieva
Author-email: peredereeva@gmail.com
License: MIT
Keywords: data envelopment analysis
Platform: UNKNOWN
Classifier: Development Status :: 4 - Beta
Classifier: Intended Audience :: Science/Research
Classifier: Topic :: Scientific/Engineering
Classifier: License :: OSI Approved :: MIT License
Classifier: Programming Language :: Python :: 3.3
Classifier: Programming Language :: Python :: 3.4
Classifier: Programming Language :: Python :: 3.5
Classifier: Operating System :: Microsoft :: Windows
Classifier: Operating System :: POSIX :: Linux
Requires-Dist: openpyxl
Requires-Dist: pulp (>=1.6.1)
Requires-Dist: xlrd
Requires-Dist: xlwt-future
